setup.py
cmdtool/__init__.py
cmdtool/actions.py
cmdtool/base_command.py
cmdtool/command.py
cmdtool/end_command.py
cmdtool/sub_command.py
cmdtool/super_command.py
cmdtool.egg-info/PKG-INFO
cmdtool.egg-info/SOURCES.txt
cmdtool.egg-info/dependency_links.txt
cmdtool.egg-info/not-zip-safe
cmdtool.egg-info/top_level.txt