Metadata-Version: 1.0
Name: cmdtool
Version: 0.2
Summary: A very basic framework for writing command line tools
Home-page: https://github.com/ConnorDillon/cmdtool
Author: Connor Dillon
Author-email: connor@cdillon.nl
License: GPLv3
Platform: UNKNOWN
